csvdedupe/__init__.py
csvdedupe/csvdedupe.py
csvdedupe/csvhelpers.py
csvdedupe/csvlink.py
csvdedupe-0.1.20.dist-info/LICENSE.md
csvdedupe-0.1.20.dist-info/METADATA
csvdedupe-0.1.20.dist-info/WHEEL
csvdedupe-0.1.20.dist-info/entry_points.txt
csvdedupe-0.1.20.dist-info/top_level.txt
csvdedupe-0.1.20.dist-info/RECORD
