Metadata-Version: 2.1
Name: csvdedupe
Version: 0.1.20
Summary: Command line tools for deduplicating and merging csv files
Home-page: UNKNOWN
Author: Forest Gregg, Derek Eder
License: MIT
Platform: UNKNOWN
Requires-Dist: future (>=0.14)
Requires-Dist: dedupe (<2,>=1.6)
